wow_ai_hub/__init__.py
wow_ai_hub/_commit_api.py
wow_ai_hub/_commit_scheduler.py
wow_ai_hub/_login.py
wow_ai_hub/_multi_commits.py
wow_ai_hub/_snapshot_download.py
wow_ai_hub/_space_api.py
wow_ai_hub/_tensorboard_logger.py
wow_ai_hub/_webhooks_payload.py
wow_ai_hub/_webhooks_server.py
wow_ai_hub/commands/__init__.py
wow_ai_hub/commands/_cli_utils.py
wow_ai_hub/commands/delete_cache.py
wow_ai_hub/commands/download.py
wow_ai_hub/commands/env.py
wow_ai_hub/commands/huggingface_cli.py
wow_ai_hub/commands/lfs.py
wow_ai_hub/commands/scan_cache.py
wow_ai_hub/commands/upload.py
wow_ai_hub/commands/user.py
wow_ai_hub/community.py
wow_ai_hub/constants.py
wow_ai_hub/fastai_utils.py
wow_ai_hub/file_download.py
wow_ai_hub/hf_api.py
wow_ai_hub/hf_file_system.py
wow_ai_hub/hub_mixin.py
wow_ai_hub/inference/__init__.py
wow_ai_hub/inference/_client.py
wow_ai_hub/inference/_common.py
wow_ai_hub/inference/_generated/__init__.py
wow_ai_hub/inference/_generated/_async_client.py
wow_ai_hub/inference/_text_generation.py
wow_ai_hub/inference/_types.py
wow_ai_hub/inference_api.py
wow_ai_hub/keras_mixin.py
wow_ai_hub/lfs.py
wow_ai_hub/repocard.py
wow_ai_hub/repocard_data.py
wow_ai_hub/repository.py
wow_ai_hub/templates/datasetcard_template.md
wow_ai_hub/templates/modelcard_template.md
wow_ai_hub/utils/__init__.py
wow_ai_hub/utils/_cache_assets.py
wow_ai_hub/utils/_cache_manager.py
wow_ai_hub/utils/_chunk_utils.py
wow_ai_hub/utils/_datetime.py
wow_ai_hub/utils/_deprecation.py
wow_ai_hub/utils/_errors.py
wow_ai_hub/utils/_experimental.py
wow_ai_hub/utils/_fixes.py
wow_ai_hub/utils/_git_credential.py
wow_ai_hub/utils/_headers.py
wow_ai_hub/utils/_hf_folder.py
wow_ai_hub/utils/_http.py
wow_ai_hub/utils/_pagination.py
wow_ai_hub/utils/_paths.py
wow_ai_hub/utils/_runtime.py
wow_ai_hub/utils/_subprocess.py
wow_ai_hub/utils/_telemetry.py
wow_ai_hub/utils/_typing.py
wow_ai_hub/utils/_validators.py
wow_ai_hub/utils/endpoint_helpers.py
wow_ai_hub/utils/logging.py
wow_ai_hub/utils/sha.py
wow_ai_hub-0.0.3.dist-info/METADATA
wow_ai_hub-0.0.3.dist-info/WHEEL
wow_ai_hub-0.0.3.dist-info/RECORD
